soph/__init__.py
soph/nn/__init__.py
soph/nn/nn.py
soph/utils/__init__.py
soph/utils/utils.py
tests/__init__.py
soph-0.2.2.dist-info/LICENSE-MIT
soph-0.2.2.dist-info/METADATA
soph-0.2.2.dist-info/WHEEL
soph-0.2.2.dist-info/top_level.txt
soph-0.2.2.dist-info/RECORD
