Metadata-Version: 2.1
Name: soph
Version: 0.2.2
Summary: Tools I find useful
Home-page: https://github.com/artificialsoph/soph.py
Author: artificialsoph
Author-email: s@soph.info
Maintainer: artificialsoph
Maintainer-email: s@soph.info
License: MIT
Platform: UNKNOWN
Classifier: Development Status :: 4 - Beta
Classifier: Intended Audience :: Developers
Classifier: License :: OSI Approved :: MIT License
Classifier: Natural Language :: English
Classifier: Operating System :: OS Independent
Classifier: Programming Language :: Python :: 2.7
Classifier: Programming Language :: Python :: 3.5
Classifier: Programming Language :: Python :: 3.6
Classifier: Programming Language :: Python :: Implementation :: CPython
Classifier: Programming Language :: Python :: Implementation :: PyPy
Requires-Dist: keras
Requires-Dist: matplotlib (>=3.1)
Requires-Dist: numpy
Requires-Dist: seaborn
Requires-Dist: sklearn
Requires-Dist: pylint
